pruby/__init__.py
pruby/calculator.py
pruby/constants.py
pruby/engine.py
pruby/gui/__init__.py
pruby/gui/app.py
pruby/gui/gridable.py
pruby/gui/popups.py
pruby/resources/__init__.py
pruby/resources/icon.gif
pruby/spectrum/__init__.py
pruby/spectrum/curve.py
pruby/spectrum/spectrum.py
pruby/strategies/__init__.py
pruby/strategies/backfitting.py
pruby/strategies/base.py
pruby/strategies/correcting.py
pruby/strategies/drawing.py
pruby/strategies/peakfitting.py
pruby/strategies/reading.py
pruby/strategies/translating.py
pruby/utility/__init__.py
pruby/utility/cycle.py
pruby/utility/functions.py
pruby/utility/line_subset.py
test/__init__.py
test/test_calculator.py
test/test_data1.txt
test/test_data2.txt
test/test_resources.py
test/test_spectrum.py
test/test_utility.py
pruby-0.1.3.dist-info/LICENSE.txt
pruby-0.1.3.dist-info/METADATA
pruby-0.1.3.dist-info/WHEEL
pruby-0.1.3.dist-info/top_level.txt
pruby-0.1.3.dist-info/RECORD
