Metadata-Version: 2.1
Name: pruby
Version: 0.1.3
Summary: Python library for calculating pressure based on ruby fluorescence
Home-page: https://github.com/Baharis/pRuby
Author: Daniel Tchoń
Author-email: dtchon@chem.uw.edu.pl
License: MIT
Classifier: Development Status :: 3 - Alpha
Classifier: Environment :: Console
Classifier: Intended Audience :: Science/Research
Classifier: License :: OSI Approved :: MIT License
Classifier: Natural Language :: English
Classifier: Operating System :: OS Independent
Classifier: Programming Language :: Python
Classifier: Programming Language :: Python :: 3
Classifier: Programming Language :: Python :: 3.6
Classifier: Programming Language :: Python :: 3.7
Classifier: Programming Language :: Python :: 3.8
Classifier: Programming Language :: Python :: 3.9
Classifier: Programming Language :: Python :: 3.10
Classifier: Programming Language :: Python :: 3.11
Classifier: Programming Language :: Python :: 3.12
Classifier: Programming Language :: Python :: 3 :: Only
Classifier: Topic :: Scientific/Engineering
Classifier: Topic :: Scientific/Engineering :: Chemistry
Classifier: Topic :: Scientific/Engineering :: Physics
License-File: LICENSE.txt
Requires-Dist: matplotlib (!=3.3.*,>=3.0.0)
Requires-Dist: numpy (>=1.18.1)
Requires-Dist: scipy (>=1.5.1)
Requires-Dist: uncertainties (>=3.*)
Requires-Dist: natsort (==8.*)
